quant_metrics/__init__.py
quant_metrics/utils.py
optego_quant_metrics-1.0.3.dist-info/METADATA
optego_quant_metrics-1.0.3.dist-info/WHEEL
optego_quant_metrics-1.0.3.dist-info/licenses/LICENSE
optego_quant_metrics-1.0.3.dist-info/RECORD
