Metadata-Version: 2.4
Name: optego-quant-metrics
Version: 1.0.3
Summary: A Python package for quantitative portfolio metrics calculations, including Deflated Sharpe Ratio (DSR)
Project-URL: Homepage, https://github.com/optego/quant-metrics
Project-URL: Repository, https://github.com/optego/quant-metrics
Author: Optego
License-File: LICENSE
Keywords: dsr,finance,metrics,portfolio,quantitative,sharpe-ratio
Classifier: Development Status :: 4 - Beta
Classifier: Intended Audience :: Developers
Classifier: Intended Audience :: Financial and Insurance Industry
Classifier: License :: OSI Approved :: MIT License
Classifier: Programming Language :: Python :: 3
Classifier: Programming Language :: Python :: 3.12
Classifier: Topic :: Office/Business :: Financial :: Investment
Requires-Python: >=3.12
Requires-Dist: numpy>=1.24.0
Requires-Dist: scipy>=1.10.0
Provides-Extra: dev
Requires-Dist: bump2version>=1.0.1; extra == 'dev'
Requires-Dist: pre-commit; extra == 'dev'
Requires-Dist: pytest-cov; extra == 'dev'
Requires-Dist: pytest>=7.0.0; extra == 'dev'
